hydrohyeto_matplotlib/__init__.py
hydrohyeto_matplotlib/hydrohyeto_matplotlib.py
hydrohyeto_matplotlib-0.1.2.dist-info/LICENSE
hydrohyeto_matplotlib-0.1.2.dist-info/METADATA
hydrohyeto_matplotlib-0.1.2.dist-info/WHEEL
hydrohyeto_matplotlib-0.1.2.dist-info/top_level.txt
hydrohyeto_matplotlib-0.1.2.dist-info/RECORD
