Metadata-Version: 2.1
Name: hydrohyeto-matplotlib
Version: 0.1.2
Summary: Generate a hydrograph and a hyetograph.
Home-page: https://github.com/yakitoritabetai/hydrohyeto-matplotlib
Download-URL: https://github.com/yakitoritabetai/hydrohyeto-matplotlib
Author: HAKOISHI Kenta
Author-email: hakoken.of.joytoy@gmail.com
Maintainer: HAKOISHI Kenta
Maintainer-email: hakoken.of.joytoy@gmail.com
License: MIT
Keywords: matplotlib
Classifier: License :: OSI Approved :: MIT License
License-File: LICENSE
Requires-Dist: japanize-matplotlib
